nabard/__init__.py
nabard/engine/__init__.py
nabard/engine/base.py
nabard/engine/robot.py
nabard/engine/turn.py
nabard/robot/__init__.py
nabard/robot/robot.py
nabard-0.1.1a0.dist-info/LICENSE
nabard-0.1.1a0.dist-info/METADATA
nabard-0.1.1a0.dist-info/WHEEL
nabard-0.1.1a0.dist-info/top_level.txt
nabard-0.1.1a0.dist-info/RECORD
